dry_core/__init__.py
dry_core/exceptions/__init__.py
dry_core/operations/__init__.py
dry_core/operations/_models.py
dry_core/operations/_utils.py
dry_core/operations/arguments.py
dry_core/operations/decorators.py
dry_core/operations/operations.py
dry_core/selectors/__init__.py
dry_core/selectors/api/__init__.py
dry_core/selectors/api/generics.py
dry_core/selectors/api/pagination.py
dry_core/selectors/generics.py
dry_core/selectors/tortoise/__init__.py
dry_core/selectors/tortoise/generics.py
dry_core/selectors/tortoise/mixins.py
dry_core/services/__init__.py
dry_core/services/generics.py
dry_core/services/mixins.py
dry_core/services/tortoise/__init__.py
dry_core/services/tortoise/generics.py
dry_core/utils/__init__.py
dry_core/utils/validators.py
dry_core-0.5.9.dist-info/METADATA
dry_core-0.5.9.dist-info/WHEEL
dry_core-0.5.9.dist-info/RECORD
